bunny/__init__.py
bunny/stream/__init__.py
bunny/stream/chapter.py
bunny/stream/collection.py
bunny/stream/exceptions.py
bunny/stream/helpers.py
bunny/stream/library.py
bunny/stream/moment.py
bunny/stream/stream_settings.py
bunny/stream/video.py
bunnycdn_api_wrapper-1.0.14.dist-info/LICENSE.MD
bunnycdn_api_wrapper-1.0.14.dist-info/METADATA
bunnycdn_api_wrapper-1.0.14.dist-info/WHEEL
bunnycdn_api_wrapper-1.0.14.dist-info/top_level.txt
bunnycdn_api_wrapper-1.0.14.dist-info/RECORD
