Metadata-Version: 2.1
Name: bunnycdn-api-wrapper
Version: 1.0.14
Summary: An API Wrapper for the Bunny.net API.
Home-page: https://github.com/hassanaziz0012/bunnycdn-stream-api
Author: Hassan Aziz
Author-email: hassanaziz0012@gmail.com
License: UNKNOWN
Project-URL: Creator Site, https://hassanaziz0012.github.io/portfolio-website/#
Platform: UNKNOWN
Classifier: Programming Language :: Python :: 3
Classifier: License :: OSI Approved :: MIT License
Classifier: Operating System :: OS Independent
Requires-Python: >=3.6
License-File: LICENSE.MD
Requires-Dist: requests
